{
  "collectionName": "components_sections_teasers",
  "info": {
    "displayName": "Teaser"
  },
  "options": {},
  "attributes": {
    "title": {
      "type": "string"
    },
    "description": {
      "type": "blocks"
    },
    "buttonText": {
      "type": "string"
    },
    "buttonLink": {
      "type": "string"
    },
    "image": {
      "type": "media",
      "multiple": false,
      "allowedTypes": [
        "images",
        "files",
        "videos",
        "audios"
      ]
    },
    "imagePosition": {
      "type": "enumeration",
      "enum": [
        "left",
        "right"
      ]
    },
    "backgroundColor": {
      "type": "string"
    }
  },
  "config": {}
}
